vulcan/__init__.py
vulcan/application.py
vulcan/service.py
signals_vulcan-1.0.1.dist-info/METADATA
signals_vulcan-1.0.1.dist-info/WHEEL
signals_vulcan-1.0.1.dist-info/top_level.txt
signals_vulcan-1.0.1.dist-info/RECORD
